polyfeatures/__init__.py
polyfeatures/analyze.py
polyfeatures/calculate_features.py
polyfeatures/polyfeatures-testing.py
polyfeatures/processing.py
polyfeatures-0.0.28.dist-info/licenses/LICENSE
polyfeatures-0.0.28.dist-info/METADATA
polyfeatures-0.0.28.dist-info/WHEEL
polyfeatures-0.0.28.dist-info/top_level.txt
polyfeatures-0.0.28.dist-info/RECORD
