Metadata-Version: 2.4
Name: polyfeatures
Version: 0.0.28
Summary: A python package for featurizing polymers.
Author: Reyansh Saindane
Author-email: <reyansh.saindane@gmail.com>
Keywords: python
Classifier: Intended Audience :: Developers
Classifier: Programming Language :: Python :: 3
Classifier: Operating System :: Unix
Classifier: Operating System :: MacOS :: MacOS X
Classifier: Operating System :: Microsoft :: Windows
License-File: LICENSE
Requires-Dist: rdkit
Requires-Dist: networkx
Requires-Dist: joblib
Requires-Dist: tqdm
Requires-Dist: pandas
Requires-Dist: numpy
Dynamic: author
Dynamic: author-email
Dynamic: classifier
Dynamic: keywords
Dynamic: license-file
Dynamic: requires-dist
Dynamic: summary
